redis_limit/__init__.py
redis_limit/conf.py
redis_limit/limit.py
redis_limit/lock.py
redis_limit/lua_script.py
redis_limit-0.0.3.dist-info/METADATA
redis_limit-0.0.3.dist-info/WHEEL
redis_limit-0.0.3.dist-info/top_level.txt
redis_limit-0.0.3.dist-info/RECORD
